sphinxcontrib_ansi_rai-0.7.0.dev20250623-py3.12-nspkg.pth
sphinxcontrib/ansi.py
sphinxcontrib/black-on-white.css
sphinxcontrib_ansi_rai-0.7.0.dev20250623.dist-info/licenses/LICENSE
sphinxcontrib_ansi_rai-0.7.0.dev20250623.dist-info/METADATA
sphinxcontrib_ansi_rai-0.7.0.dev20250623.dist-info/WHEEL
sphinxcontrib_ansi_rai-0.7.0.dev20250623.dist-info/namespace_packages.txt
sphinxcontrib_ansi_rai-0.7.0.dev20250623.dist-info/top_level.txt
sphinxcontrib_ansi_rai-0.7.0.dev20250623.dist-info/RECORD
