Metadata-Version: 2.4
Name: sphinxcontrib-ansi-rai
Version: 0.7.0.dev20250623
Summary: Sphinx extension ansi
Home-page: https://github.com/sphinx-contrib/ansi
Download-URL: http://pypi.org/project/sphinxcontrib-ansi
Author: Sebastian Wiesner
Author-email: lunaryorn@googlemail.com
License: BSD
Platform: any
Classifier: Development Status :: 4 - Beta
Classifier: Environment :: Console
Classifier: Environment :: Web Environment
Classifier: Intended Audience :: Developers
Classifier: License :: OSI Approved :: BSD License
Classifier: Operating System :: OS Independent
Classifier: Programming Language :: Python
Classifier: Topic :: Documentation
Classifier: Topic :: Utilities
License-File: LICENSE
Requires-Dist: sphinx>=1.6
Dynamic: author
Dynamic: author-email
Dynamic: classifier
Dynamic: description
Dynamic: download-url
Dynamic: home-page
Dynamic: license
Dynamic: license-file
Dynamic: platform
Dynamic: requires-dist
Dynamic: summary
